tart_tools/__init__.py
tart_tools/api_handler.py
tart_tools/api_imaging.py
tart_tools/archive_handler.py
tart_tools/common_api.py
tart_tools/scripts/__init__.py
tart_tools/scripts/tart_calibrate.py
tart_tools/scripts/tart_calibration_data.py
tart_tools/scripts/tart_calibration_data_new.py
tart_tools/scripts/tart_download_antenna_positions.py
tart_tools/scripts/tart_download_data.py
tart_tools/scripts/tart_download_gains.py
tart_tools/scripts/tart_get_archive_data.py
tart_tools/scripts/tart_image.py
tart_tools/scripts/tart_set_mode.py
tart_tools/scripts/tart_test_api.py
tart_tools/scripts/tart_upload_antenna_positions.py
tart_tools/scripts/tart_upload_gains.py
tart_tools/scripts/tart_vis2json.py
tart_tools/test/__init__.py
tart_tools/test/test_api.py
tart_tools/test/test_imaging.py
tart_tools-1.4.5.dist-info/METADATA
tart_tools-1.4.5.dist-info/WHEEL
tart_tools-1.4.5.dist-info/entry_points.txt
tart_tools-1.4.5.dist-info/licenses/LICENSE.txt
tart_tools-1.4.5.dist-info/RECORD
