Metadata-Version: 2.4
Name: tart_tools
Version: 1.4.5
Summary: Transient Array Radio Telescope Command Line Tools
Project-URL: Homepage, http://github.com/tmolteno/tart_modules
Author-email: Tim Molteno <tim@elec.ac.nz>
License-Expression: GPL-3.0-or-later
License-File: LICENSE.txt
Classifier: Development Status :: 4 - Beta
Classifier: Intended Audience :: Science/Research
Classifier: License :: OSI Approved :: GNU General Public License v3 (GPLv3)
Classifier: Programming Language :: Python :: 3
Classifier: Topic :: Communications :: Ham Radio
Classifier: Topic :: Scientific/Engineering
Requires-Python: >=3.11
Requires-Dist: minio
Requires-Dist: numpy
Requires-Dist: requests
Requires-Dist: tart
Requires-Dist: tqdm
